syne_tune/__init__.py
syne_tune/config_space.py
syne_tune/constants.py
syne_tune/num_gpu.py
syne_tune/report.py
syne_tune/results_callback.py
syne_tune/stopping_criterion.py
syne_tune/tuner.py
syne_tune/tuner_callback.py
syne_tune/tuner_logger.py
syne_tune/tuning_status.py
syne_tune/util.py
syne_tune/version
syne_tune/backend/__init__.py
syne_tune/backend/local_backend.py
syne_tune/backend/time_keeper.py
syne_tune/backend/trial_backend.py
syne_tune/backend/trial_status.py
syne_tune/backend/python_backend/__init__.py
syne_tune/backend/python_backend/python_backend.py
syne_tune/backend/python_backend/python_entrypoint.py
syne_tune/backend/simulator_backend/__init__.py
syne_tune/backend/simulator_backend/events.py
syne_tune/backend/simulator_backend/simulator_backend.py
syne_tune/backend/simulator_backend/simulator_callback.py
syne_tune/backend/simulator_backend/time_keeper.py
syne_tune/blackbox_repository/__init__.py
syne_tune/blackbox_repository/blackbox.py
syne_tune/blackbox_repository/blackbox_offline.py
syne_tune/blackbox_repository/blackbox_surrogate.py
syne_tune/blackbox_repository/blackbox_tabular.py
syne_tune/blackbox_repository/repository.py
syne_tune/blackbox_repository/serialize.py
syne_tune/blackbox_repository/simulated_tabular_backend.py
syne_tune/blackbox_repository/utils.py
syne_tune/blackbox_repository/conversion_scripts/__init__.py
syne_tune/blackbox_repository/conversion_scripts/blackbox_recipe.py
syne_tune/blackbox_repository/conversion_scripts/generate_and_upload_all_blackboxes.py
syne_tune/blackbox_repository/conversion_scripts/recipes.py
syne_tune/blackbox_repository/conversion_scripts/utils.py
syne_tune/blackbox_repository/conversion_scripts/scripts/__init__.py
syne_tune/blackbox_repository/conversion_scripts/scripts/autoencodix_import.py
syne_tune/blackbox_repository/conversion_scripts/scripts/fcnet_import.py
syne_tune/blackbox_repository/conversion_scripts/scripts/hpob_import.py
syne_tune-0.15.0.dist-info/licenses/LICENSE
syne_tune-0.15.0.dist-info/licenses/NOTICE
syne_tune-0.15.0.dist-info/METADATA
syne_tune-0.15.0.dist-info/WHEEL
syne_tune-0.15.0.dist-info/top_level.txt
syne_tune-0.15.0.dist-info/RECORD
