Metadata-Version: 2.4
Name: syne-tune
Version: 0.15.0
Summary: A Hyperparameter Optimization Library
Author: Syne Tune Developers
License: Apache-2.0
Project-URL: Homepage, https://github.com/syne-tune/syne-tune
Project-URL: Bug Tracker, https://github.com/syne-tune/syne-tune/issues
Classifier: Development Status :: 3 - Alpha
Classifier: Intended Audience :: Developers
Classifier: Intended Audience :: Science/Research
Classifier: Topic :: Scientific/Engineering :: Artificial Intelligence
Classifier: License :: OSI Approved :: Apache Software License
Classifier: Programming Language :: Python :: 3.8
Requires-Python: >=3.8
License-File: LICENSE
License-File: NOTICE
Requires-Dist: numpy<1.27.0,>=1.22.0
Requires-Dist: dill>=0.3.6
Requires-Dist: pandas
Requires-Dist: typing_extensions
Requires-Dist: sortedcontainers
Requires-Dist: statsmodels
Requires-Dist: scikit-learn
Requires-Dist: xgboost
Requires-Dist: tqdm
Provides-Extra: dev
Requires-Dist: pytest; extra == "dev"
Requires-Dist: pytest-cov~=4.1.0; extra == "dev"
Requires-Dist: pytest-timeout; extra == "dev"
Requires-Dist: black==22.3.0; extra == "dev"
Requires-Dist: flake8; extra == "dev"
Requires-Dist: sphinx<8.0.0; extra == "dev"
Requires-Dist: nbsphinx; extra == "dev"
Requires-Dist: ipykernel; extra == "dev"
Requires-Dist: pypandoc_binary; extra == "dev"
Requires-Dist: sphinx-rtd-theme; extra == "dev"
Requires-Dist: sphinx-autodoc-typehints; extra == "dev"
Requires-Dist: traitlets<=5.11.2; extra == "dev"
Requires-Dist: myst-parser; extra == "dev"
Requires-Dist: sphinx_copybutton; extra == "dev"
Requires-Dist: sphinxcontrib-bibtex; extra == "dev"
Requires-Dist: sphinxcontrib.jquery; extra == "dev"
Requires-Dist: wheel; extra == "dev"
Provides-Extra: extra
Requires-Dist: syne-tune[dev]; extra == "extra"
Requires-Dist: numpy<1.27.0,>=1.16.0; extra == "extra"
Requires-Dist: pandas; extra == "extra"
Requires-Dist: scikit-learn; extra == "extra"
Requires-Dist: xgboost; extra == "extra"
Requires-Dist: fastparquet; extra == "extra"
Requires-Dist: h5py; extra == "extra"
Requires-Dist: huggingface_hub; extra == "extra"
Requires-Dist: onnxruntime>=1.10.0; extra == "extra"
Requires-Dist: pyyaml; extra == "extra"
Requires-Dist: configspace<=0.6.1; extra == "extra"
Requires-Dist: pandas; extra == "extra"
Requires-Dist: yahpo-gym; extra == "extra"
Requires-Dist: botorch>=0.7.2; extra == "extra"
Requires-Dist: swig; extra == "extra"
Requires-Dist: smac>=2.0; extra == "extra"
Requires-Dist: pymoo>=0.6.0; extra == "extra"
Dynamic: license-file
